main.py
sj_mcp_test2-0.1.0.dist-info/METADATA
sj_mcp_test2-0.1.0.dist-info/WHEEL
sj_mcp_test2-0.1.0.dist-info/top_level.txt
sj_mcp_test2-0.1.0.dist-info/RECORD
