Metadata-Version: 2.4
Name: sj-mcp-test2
Version: 0.1.0
Summary: 在文件中写入内容
Requires-Python: >=3.13
Requires-Dist: mcp[cli]>=1.14.1
